Metadata-Version: 1.0
Name: dperf
Version: 0.0.1
Summary: Deep Learning System Performance Profiler
Home-page: https://cn.linkedin.com/in/lycheenice
Author: lychee
Author-email: lycheenice@gmail.com
License: UNKNOWN
Platform: UNKNOWN
